spotylist.py
spotylist-0.1.0.dist-info/LICENSE
spotylist-0.1.0.dist-info/METADATA
spotylist-0.1.0.dist-info/WHEEL
spotylist-0.1.0.dist-info/entry_points.txt
spotylist-0.1.0.dist-info/top_level.txt
spotylist-0.1.0.dist-info/RECORD
