Metadata-Version: 2.1
Name: spotylist
Version: 0.1.0
Summary: Spotify in the Terminal CLI
Home-page: https://github.com/marinkres/spotylist
Author: Marin
Author-email: your.email@example.com
Classifier: Programming Language :: Python :: 3
Classifier: License :: OSI Approved :: MIT License
Classifier: Operating System :: OS Independent
Requires-Python: >=3.6
License-File: LICENSE
Requires-Dist: Click
Requires-Dist: requests
Requires-Dist: tabulate
